aiger_js/__init__.py
aiger_js/aig2js.py
py_aiger_js-0.1.1.dist-info/LICENSE
py_aiger_js-0.1.1.dist-info/WHEEL
py_aiger_js-0.1.1.dist-info/METADATA
py_aiger_js-0.1.1.dist-info/RECORD
